CryptoC/__init__.py
CryptoC/caesar.py
CryptoC/hillcipher.py
CryptoC/monoalphabetic.py
CryptoC/playfair.py
CryptoC/vernam.py
CryptoC/vigenere.py
cryptoc-1.0.0.dist-info/licenses/LICENSE
cryptoc-1.0.0.dist-info/METADATA
cryptoc-1.0.0.dist-info/WHEEL
cryptoc-1.0.0.dist-info/top_level.txt
cryptoc-1.0.0.dist-info/RECORD
