Metadata-Version: 2.4
Name: CryptoC
Version: 1.0.0
Summary: A library for various cryptography algorithms (Caesar, Hill Cipher.)
Home-page: https://github.com/hemanamo/CryptoC
Author: Ibrahem Abo kila
Author-email: ibrahemabokila@gmail.com
Classifier: Programming Language :: Python :: 3
Classifier: License :: OSI Approved :: MIT License
Classifier: Operating System :: OS Independent
Requires-Python: >=3.6
License-File: LICENSE
Dynamic: author
Dynamic: author-email
Dynamic: classifier
Dynamic: description
Dynamic: description-content-type
Dynamic: home-page
Dynamic: license-file
Dynamic: requires-python
Dynamic: summary
